mutation_simulator/__init__.py
mutation_simulator/__main__.py
mutation_simulator/_version.py
mutation_simulator/argument_parser.py
mutation_simulator/bedpe_writer.py
mutation_simulator/colors.py
mutation_simulator/defaults.py
mutation_simulator/fasta_writer.py
mutation_simulator/it_mutator.py
mutation_simulator/mut_types.py
mutation_simulator/mutator.py
mutation_simulator/rmt.py
mutation_simulator/util.py
mutation_simulator/vcf_writer.py
mutation_simulator-3.0.2.dist-info/entry_points.txt
mutation_simulator-3.0.2.dist-info/LICENSE
mutation_simulator-3.0.2.dist-info/WHEEL
mutation_simulator-3.0.2.dist-info/METADATA
mutation_simulator-3.0.2.dist-info/RECORD
