Metadata-Version: 2.1
Name: Mutation-Simulator
Version: 3.0.2
Summary: A tool for simulating random mutations in any genome
Keywords: Mutation,Simulation,Genome,SNP,SNPs,SV,SVs,Bioinformatics
Author: Marius Kühl
Requires-Python: >=3.10
Classifier: Programming Language :: Python :: 3
Classifier: License :: OSI Approved :: GNU General Public License v3 (GPLv3)
Classifier: Operating System :: POSIX :: Linux
Requires-Dist: numpy
Requires-Dist: pyfaidx
Requires-Dist: tqdm
Project-URL: Bug-Tracker, https://github.com/mkpython3/Mutation-Simulator/issues
Project-URL: Homepage, https://github.com/mkpython3/Mutation-Simulator
Project-URL: RMT-Documentation, https://github.com/mkpython3/Mutation-Simulator/blob/master/rmt-docs.pdf
